flowlang/.gitignore
flowlang/LICENSE
flowlang/README.md
flowlang/__init__.py
flowlang/core/__init__.py
flowlang/core/models/__init__.py
flowlang/core/models/base.py
flowlang/core/models/openai_model.py
flowlang/core/scenarios/__init__.py
flowlang/core/scenarios/base.py
flowlang/core/steps/__init__.py
flowlang/core/steps/base.py
flowlang/core/steps/helpers/__init__.py
flowlang/core/steps/helpers/apicall_step.py
flowlang/core/steps/helpers/control_step.py
flowlang/core/steps/helpers/summarization_step.py
flowlang/core/steps/helpers/translation_step.py
flowlang/core/steps/helpers/validation_step.py
flowlang/core/steps/required/__init__.py
flowlang/core/steps/required/end_step.py
flowlang/core/steps/required/start_step.py
flowlang-0.0.5.dist-info/METADATA
flowlang-0.0.5.dist-info/WHEEL
flowlang-0.0.5.dist-info/licenses/LICENSE
flowlang-0.0.5.dist-info/RECORD
